{
  "git_head": "882388f551ad9ed86c9ccd7d89ef9eabff989f15",
  "files": {
    "governance_md": true,
    "security_md": true,
    "release_md": true,
    "post_scrub_notice": true,
    "phase0_1_completion": true,
    "revocation_ledger": true,
    "proof_dsl": true,
    "manifold": true,
    "arbiter_kernel": true
  },
  "ci": {
    "bandit": true,
    "safety": true,
    "mypy": true,
    "sbom": true,
    "adversarial_tests": true,
    "all_present": true
  },
  "ethical_enforcement": true,
  "revocation_support": true,
  "acceptance_script": true,
  "revocation_chain_ok": true,
  "tests": {
    "bias": {
      "marker": "kt_bias",
      "returncode": 0,
      "output": ".                                                                        [100%]\n1 passed, 121 deselected in 1.38s\n"
    },
    "emotion": {
      "marker": "kt_emotion",
      "returncode": 0,
      "output": "..                                                                       [100%]\n2 passed, 120 deselected in 1.42s\n"
    },
    "composition": {
      "marker": "kt_composition",
      "returncode": 0,
      "output": ".                                                                        [100%]\n1 passed, 121 deselected in 1.31s\n"
    }
  },
  "counterfactual_risk": 0.12890625,
  "pceb_chain_ok": true,
  "emotion_drift_chain_ok": true,
  "mvp2_compliance": true
}
